Metadata-Version: 2.1
Name: Hocrox
Version: 0.3.0
Summary: Hocrox is an image preprocessing and augmentation library. It provides a Keras like simple interface to make preprocessing and augmentation pipelines.
Author: Abhishek Chatterjee
Author-email: Abhishek.Chatterjee97@protonmail.com
License: UNKNOWN
Project-URL: Bug Tracker, https://github.com/imdeepmind/hocrox/issues
Project-URL: Documentation, https://hocrox.imdeepmind.com/
Project-URL: Source Code, https://github.com/imdeepmind/hocrox
Platform: UNKNOWN
Classifier: Operating System :: OS Independent
Classifier: Development Status :: 3 - Alpha
Classifier: Intended Audience :: Developers
Classifier: Intended Audience :: Education
Classifier: Intended Audience :: Science/Research
Classifier: License :: OSI Approved :: MIT License
Classifier: Programming Language :: Python :: 3
Classifier: Programming Language :: Python :: 3.6
Classifier: Programming Language :: Python :: 3.7
Classifier: Programming Language :: Python :: 3.8
Classifier: Programming Language :: Python :: 3.9
Requires-Python: >=3.6
License-File: LICENSE
Requires-Dist: opencv-python
Requires-Dist: tqdm
Requires-Dist: prettytable
